star_dresden_gs_lib/__init__.py
star_dresden_gs_lib/main.py
star_dresden_gs_lib/components/__init__.py
star_dresden_gs_lib/components/getter.py
star_dresden_gs_lib/components/logs.py
star_dresden_gs_lib/components/setter.py
star_dresden_gs_lib-0.2.0.dist-info/LICENSE.txt
star_dresden_gs_lib-0.2.0.dist-info/METADATA
star_dresden_gs_lib-0.2.0.dist-info/WHEEL
star_dresden_gs_lib-0.2.0.dist-info/top_level.txt
star_dresden_gs_lib-0.2.0.dist-info/RECORD
