Metadata-Version: 2.1
Name: star_dresden_gs_lib
Version: 0.2.0
Summary: A framework for creating a groundstation with grpc and PyQt6
Home-page: https://www.star-dresden.de
Author: STAR Dresden e.V.
Author-email: Lars Reiche <sners03coding@gmail.com>
Project-URL: Homepage, https://github.com/pypa/sampleproject
Project-URL: Issues, https://github.com/pypa/sampleproject/issues
Classifier: Programming Language :: Python :: 3
Classifier: License :: OSI Approved :: MIT License
Classifier: Operating System :: OS Independent
Requires-Python: >=3.10, <4
License-File: LICENSE.txt
